statsPackage/__init__.py
statsPackage/test.py
statsPackage/testPandas.py
statsPackage/testSatelStats.py
testSatelProjectRepo-0.0.5.dist-info/LICENSE
testSatelProjectRepo-0.0.5.dist-info/METADATA
testSatelProjectRepo-0.0.5.dist-info/WHEEL
testSatelProjectRepo-0.0.5.dist-info/top_level.txt
testSatelProjectRepo-0.0.5.dist-info/RECORD
