Metadata-Version: 2.1
Name: testSatelProjectRepo
Version: 0.0.5
Summary: testing first package Satel stats
Home-page: https://github.com/juanedomb/testSatelProjectRepo
Author: Juan Dombald
License: MIT
Platform: UNKNOWN
License-File: LICENSE
